oarepo_actions/__init__.py
oarepo_actions/config.py
oarepo_actions/decorators.py
oarepo_actions/ext.py
oarepo_actions/permissions.py
oarepo_actions/record_action.py
oarepo_actions/record_action_list.py
oarepo_actions/version.py
oarepo_actions-1.0.7.dist-info/LICENSE
oarepo_actions-1.0.7.dist-info/METADATA
oarepo_actions-1.0.7.dist-info/WHEEL
oarepo_actions-1.0.7.dist-info/entry_points.txt
oarepo_actions-1.0.7.dist-info/top_level.txt
oarepo_actions-1.0.7.dist-info/RECORD
