Metadata-Version: 2.1
Name: oarepo-actions
Version: 1.0.7
Summary: Invenio digital library framework.
Home-page: https://github.com/oarepo-actions/oarepo-actions
Author: Alzbeta Pokorna
Author-email: alzbeta.pokorna@cesnet.cz
License: MIT
Keywords: oarepo-actions Invenio
Platform: any
Classifier: Environment :: Web Environment
Classifier: Intended Audience :: Developers
Classifier: License :: OSI Approved :: MIT License
Classifier: Operating System :: OS Independent
Classifier: Programming Language :: Python
Classifier: Topic :: Internet :: WWW/HTTP :: Dynamic Content
Classifier: Programming Language :: Python :: 3
Classifier: Programming Language :: Python :: 3.6
Classifier: Development Status :: 3 - Alpha
Requires-Dist: deepmerge
Requires-Dist: marshmallow
Requires-Dist: flask
Provides-Extra: tests
Requires-Dist: oarepo[tests] (~=3.3.0) ; extra == 'tests'
Requires-Dist: deepmerge ; extra == 'tests'
Requires-Dist: oarepo-mapping-includes ; extra == 'tests'
Requires-Dist: oarepo-validate ; extra == 'tests'
Requires-Dist: oarepo-invenio-model ; extra == 'tests'
Provides-Extra: tests-es7
Requires-Dist: oarepo[tests-es7] (~=3.3.0) ; extra == 'tests-es7'
Requires-Dist: deepmerge ; extra == 'tests-es7'
Requires-Dist: oarepo-mapping-includes ; extra == 'tests-es7'
Requires-Dist: oarepo-validate ; extra == 'tests-es7'
Requires-Dist: oarepo-invenio-model ; extra == 'tests-es7'
